{
  "coord": {
    "lon": -0.1257,
    "lat": 51.5085
  },
  "weather": [
    {
      "id": 803,
      "main": "Clouds",
      "description": "broken clouds",
      "icon": "04d"
    }
  ],
  "base": "stations",
  "main": {
    "temp": 12.44,
    "feels_like": 10.81,
    "temp_min": 11.11,
    "temp_max": 13.88,
    "pressure": 1020,
    "humidity": 41,
    "sea_level": 1020,
    "grnd_level": 1015
  },
  "visibility": 10000,
  "wind": {
    "speed": 2.57,
    "deg": 70
  },
  "clouds": {
    "all": 57
  },
  "dt": 1774098030,
  "sys": {
    "type": 2,
    "id": 268730,
    "country": "GB",
    "sunrise": 1774072880,
    "sunset": 1774116845
  },
  "timezone": 0,
  "id": 2643743,
  "name": "London",
  "cod": 200,
  "_last_updated_utc": "2026-03-21T13:03:14.542Z"
}